setup.py
vm.py
PySimpVM.egg-info/PKG-INFO
PySimpVM.egg-info/SOURCES.txt
PySimpVM.egg-info/dependency_links.txt
PySimpVM.egg-info/top_level.txt
vm/__init__.py
vm/corefuncs.py
vm/exceptions.py
vm/killer.py
vm/math.py
vm/printer.py