Metadata-Version: 1.0
Name: PySimpVM
Version: 0.4
Summary: A python vm with simple functions.
Home-page: UNKNOWN
Author: Anirudh Balaji
Author-email: anirudhqazxswced@gmail.com
License: PSF
Keywords: vm python simple functions
Platform: UNKNOWN
